LICENSE
MANIFEST.in
README.md
setup.py
covmatic_stations/__init__.py
covmatic_stations/geometry.py
covmatic_stations/hardware.py
covmatic_stations/lights.py
covmatic_stations/movement_manager.py
covmatic_stations/multi_tube_source.py
covmatic_stations/request.py
covmatic_stations/sound_manager.py
covmatic_stations/station.py
covmatic_stations/utils.py
covmatic_stations.egg-info/PKG-INFO
covmatic_stations.egg-info/SOURCES.txt
covmatic_stations.egg-info/dependency_links.txt
covmatic_stations.egg-info/requires.txt
covmatic_stations.egg-info/top_level.txt
covmatic_stations/a/COPAN 15 Tube Rack 14000 µL.json
covmatic_stations/a/__init__.py
covmatic_stations/a/a.py
covmatic_stations/a/aBioerPreparation.py
covmatic_stations/a/copan_24.py
covmatic_stations/a/copan_48.py
covmatic_stations/a/copan_48_correction.json
covmatic_stations/a/copan_48_saliva.py
covmatic_stations/a/p1000.py
covmatic_stations/a/p1000reload.py
covmatic_stations/a/p300.py
covmatic_stations/a/reload.py
covmatic_stations/a/technogenetics.py
covmatic_stations/a/msg/StationA.json
covmatic_stations/a/msg/StationAP1000.json
covmatic_stations/a/msg/StationAP1000Reload.json
covmatic_stations/a/msg/StationAP300.json
covmatic_stations/a/msg/StationAReloadMixin.json
covmatic_stations/a/msg/StationATechnogenetics.json
covmatic_stations/a/msg/StationATechnogenetics24.json
covmatic_stations/a/msg/StationATechnogenetics48.json
covmatic_stations/b/__init__.py
covmatic_stations/b/b.py
covmatic_stations/b/magnet_heights.json
covmatic_stations/b/magnets.py
covmatic_stations/b/nest_12_reservoir_15ml_modified.json
covmatic_stations/b/technogenetics.py
covmatic_stations/b/technogenetics_short.py
covmatic_stations/b/msg/StationB.json
covmatic_stations/b/msg/StationBTechnogenetics.json
covmatic_stations/b/msg/StationBTechnogeneticsElutionRemoval.json
covmatic_stations/b/msg/StationBTechnogeneticsWashBRemoval.json
covmatic_stations/bioer/Bioer_full_dw.py
covmatic_stations/bioer/Bioer_preparation.py
covmatic_stations/bioer/__init__.py
covmatic_stations/bioer/msg/BioerProtocol.json
covmatic_stations/c/__init__.py
covmatic_stations/c/bioer_mastermix_prep.py
covmatic_stations/c/c.py
covmatic_stations/c/technogenetics.py
