Metadata-Version: 2.1
Name: covmatic-stations
Version: 3.0.2
Summary: Package for the COVMATIC Opentrons stations
Home-page: https://github.com/covmatic/stations
Author: Marco Tiraboschi
Author-email: marco.tiraboschi@unimi.it
Maintainer: Marco Tiraboschi, Agostino Facotti, Giada Facoetti
Maintainer-email: marco.tiraboschi@unimi.it, agostino.facotti@gmail.com, giada.facoetti@hotmail.it
License: UNKNOWN
Platform: UNKNOWN
Classifier: Programming Language :: Python :: 3
Classifier: License :: OSI Approved :: MIT License
Classifier: Operating System :: OS Independent
Requires-Python: >=3.7, <3.9
License-File: LICENSE
